venumML/__init__.py
venumML/approx_functions.py
venumML/venum_tools.py
venumML/deep_learning/__init__.py
venumML/deep_learning/transformer/__init__.py
venumML/deep_learning/transformer/transformer.py
venumML/graphs/__init__.py
venumML/graphs/venum_graph.py
venumML/linear_models/__init__.py
venumML/linear_models/regression/__init__.py
venumML/linear_models/regression/linear_regression.py
venumML/linear_models/regression/logistic_regression.py
venumML/optimization/__init__.py
venumML/optimization/sgd.py
venumML/time_series/__init__.py
venumML/time_series/Phineus/__init__.py
venumML/time_series/Phineus/phineus_FFT.py
venumML/time_series/Phineus/phineus_rolling_average.py
venumML/time_series/Phineus/phineus_timeseries.py
venumML/venumpy/__init__.py
venumML/venumpy/small_glwe.py
venumML/venumpy/venumpy.abi3.so
venumML-0.2.1.dist-info/LICENSE
venumML-0.2.1.dist-info/METADATA
venumML-0.2.1.dist-info/WHEEL
venumML-0.2.1.dist-info/top_level.txt
venumML-0.2.1.dist-info/RECORD
