Metadata-Version: 2.1
Name: venumML
Version: 0.2.1
Summary: Vaultree's Encrypted Machine Learning library built on VENumpy
Home-page: https://github.com/vaultree/venumML
License: BSD-3-Clause
Classifier: License :: OSI Approved :: BSD License
License-File: LICENSE
Requires-Dist: scipy
Requires-Dist: deepface
Requires-Dist: tensorflow
Requires-Dist: matplotlib
Requires-Dist: numpy
Requires-Dist: scikit-learn
Requires-Dist: transformers
Requires-Dist: tqdm
Requires-Dist: torch
Requires-Dist: ipywidgets
Requires-Dist: widgetsnbextension
Requires-Dist: pandas-profiling
Requires-Dist: networkx
Requires-Dist: pandas
